gaitmap/__init__.py
gaitmap/_event_detection_common/__init__.py
gaitmap/_event_detection_common/_event_detection_mixin.py
gaitmap/base.py
gaitmap/data_transform/__init__.py
gaitmap/data_transform/_base.py
gaitmap/data_transform/_feature_transform.py
gaitmap/data_transform/_filter.py
gaitmap/data_transform/_scaler.py
gaitmap/evaluation_utils/__init__.py
gaitmap/evaluation_utils/event_detection.py
gaitmap/evaluation_utils/parameter_errors.py
gaitmap/evaluation_utils/scores.py
gaitmap/evaluation_utils/stride_segmentation.py
gaitmap/event_detection/__init__.py
gaitmap/event_detection/_herzer_event_detection.py
gaitmap/example_data.py
gaitmap/gait_detection/__init__.py
gaitmap/parameters/__init__.py
gaitmap/parameters/_spatial_parameters.py
gaitmap/parameters/_temporal_parameters.py
gaitmap/preprocessing/__init__.py
gaitmap/preprocessing/sensor_alignment/__init__.py
gaitmap/preprocessing/sensor_alignment/_gravity_alignment.py
gaitmap/preprocessing/sensor_alignment/_mulisensor_alignment.py
gaitmap/preprocessing/sensor_alignment/_pca_alignment.py
gaitmap/stride_segmentation/__init__.py
gaitmap/stride_segmentation/_roi_stride_segmentation.py
gaitmap/stride_segmentation/_utils.py
gaitmap/stride_segmentation/hmm.py
gaitmap/trajectory_reconstruction/__init__.py
gaitmap/trajectory_reconstruction/_region_level_trajectory.py
gaitmap/trajectory_reconstruction/_stride_level_trajectory.py
gaitmap/trajectory_reconstruction/_trajectory_wrapper.py
gaitmap/trajectory_reconstruction/orientation_methods/__init__.py
gaitmap/trajectory_reconstruction/orientation_methods/_madgwick.py
gaitmap/trajectory_reconstruction/orientation_methods/_simple_gyro_integration.py
gaitmap/trajectory_reconstruction/position_methods/__init__.py
gaitmap/trajectory_reconstruction/position_methods/_forward_backwards_integration.py
gaitmap/trajectory_reconstruction/trajectory_methods/__init__.py
gaitmap/trajectory_reconstruction/trajectory_methods/_kalman_numba_funcs.py
gaitmap-2.5.2.dist-info/LICENSE
gaitmap-2.5.2.dist-info/METADATA
gaitmap-2.5.2.dist-info/WHEEL
gaitmap-2.5.2.dist-info/RECORD
