Metadata-Version: 2.3
Name: gaitmap
Version: 2.5.2
Summary: The Gait and Movement Analysis Package - Your definite guide to reliable IMU based human movement analysis.
License: MIT
Author: Arne Küderle
Author-email: arne.kuederle@fau.de
Requires-Python: >=3.9.0,<4.0
Classifier: License :: OSI Approved :: MIT License
Classifier: Programming Language :: Python :: 3
Classifier: Programming Language :: Python :: 3.9
Classifier: Programming Language :: Python :: 3.10
Classifier: Programming Language :: Python :: 3.11
Classifier: Programming Language :: Python :: 3.12
Classifier: Programming Language :: Python :: 3.13
Provides-Extra: all
Provides-Extra: hmm
Provides-Extra: stats
Requires-Dist: joblib (>=1.2.0)
Requires-Dist: numba (>=0.55)
Requires-Dist: numba (>=0.55.2) ; sys_platform == "darwin" and platform_machine == "arm64"
Requires-Dist: numpy (>=1.20)
Requires-Dist: pandas (>=2)
Requires-Dist: pingouin (>=0.5.3) ; extra == "stats" or extra == "all"
Requires-Dist: pomegranate (>=0.14.2,<=0.14.6) ; (python_version < "3.10") and (extra == "hmm" or extra == "all")
Requires-Dist: pooch (>=1.7.0)
Requires-Dist: scikit-learn (>=1.0.1)
Requires-Dist: scipy (>=1.6.1)
Requires-Dist: tpcp (>=0.32.0)
Requires-Dist: typing_extensions (>=4.1.1)
Project-URL: Homepage, https://github.com/mad-lab-fau/gaitmap
Project-URL: Repository, https://github.com/mad-lab-fau/gaitmap
